uiua.cpython-39-darwin.so
uiuapy-0.2.0.dist-info/licenses/LICENSE
uiuapy-0.2.0.dist-info/METADATA
uiuapy-0.2.0.dist-info/WHEEL
uiuapy-0.2.0.dist-info/top_level.txt
uiuapy-0.2.0.dist-info/RECORD
